openedx_events_sender/__init__.py
openedx_events_sender/apps.py
openedx_events_sender/receivers.py
openedx_events_sender/tasks.py
openedx_events_sender/utils.py
openedx_events_sender-1.0.0.dist-info/LICENSE.txt
openedx_events_sender-1.0.0.dist-info/METADATA
openedx_events_sender-1.0.0.dist-info/WHEEL
openedx_events_sender-1.0.0.dist-info/entry_points.txt
openedx_events_sender-1.0.0.dist-info/top_level.txt
openedx_events_sender-1.0.0.dist-info/RECORD
