Metadata-Version: 2.1
Name: openedx-events-sender
Version: 1.0.0
Summary: Send Open edX events to selected URLs.
Home-page: https://github.com/open-craft/openedx-events-sender
Author: OpenCraft
Author-email: help@opencraft.com
License: AGPL 3.0
Keywords: Python edx
Platform: UNKNOWN
Classifier: Development Status :: 3 - Alpha
Classifier: Framework :: Django
Classifier: Framework :: Django :: 3.2
Classifier: Intended Audience :: Developers
Classifier: License :: OSI Approved :: GNU Affero General Public License v3 or later (AGPLv3+)
Classifier: Natural Language :: English
Classifier: Programming Language :: Python :: 3
Classifier: Programming Language :: Python :: 3.8
Requires-Python: >=3.8
License-File: LICENSE.txt
Requires-Dist: Django
Requires-Dist: celery
Requires-Dist: openedx-events
Requires-Dist: requests
